MANIFEST.in
README.md
gmreader.py
setup.py
gmreader.egg-info/PKG-INFO
gmreader.egg-info/SOURCES.txt
gmreader.egg-info/dependency_links.txt
gmreader.egg-info/entry_points.txt
gmreader.egg-info/requires.txt
gmreader.egg-info/top_level.txt