Metadata-Version: 1.0
Name: gmreader
Version: 0.1.3
Summary: Let python read your google emails to you. Listen to your gmails instead of reading them
Home-page: http://github.com/jawerty/gmreader
Author: Jared Wright
Author-email: jawerty210@gmail.com
License: MIT
Keywords: email gmail google mail read text to speech
Platform: UNKNOWN
